kb/__init__.py
kb/cli.py
kb/config.py
kb/config_template.toml
kb/hashing.py
kb/ignores.py
kb/api/__init__.py
kb/api/app.py
kb/api/search_backend.py
kb/api/server.py
kb/cache/__init__.py
kb/cache/cache.py
kb/chunkers/__init__.py
kb/chunkers/fallback_chunker.py
kb/chunkers/md_chunker.py
kb/chunkers/py_chunker.py
kb/chunkers/registry.py
kb/chunkers/repo_config.py
kb/chunkers/token_utils.py
kb/chunkers/ts_chunker.py
kb/chunkers/types.py
kb/embeddings/provider.py
kb/ingest/__init__.py
kb/ingest/_helpers.py
kb/ingest/cli.py
kb/ingest/dedup.py
kb/ingest/error_logging.py
kb/ingest/lang.py
kb/ingest/pipeline.py
kb/ingest/scanner.py
kb/retrieval/__init__.py
kb/retrieval/ann_tuning.py
kb/retrieval/cross_encoder_rerank.py
kb/retrieval/rankers.py
kb/retrieval/types.py
kb/store/__init__.py
kb/store/lancedb_store.py
kb/store/sql_models.py
kb/store/sqlite_meta.py
personas/__init__.py
personas/__main__.py
personas/cast/big-balls/persona.toml
personas/cast/big-balls/prompt.md
personas/cast/chief-of-staff/persona.toml
personas/cast/chief-of-staff/system.md
personas/cast/deep-dive/persona.toml
personas/cast/deep-dive/prompt.md
personas/cast/fancy-slave/persona.toml
personas/cast/fancy-slave/prompt.md
personas/cast/journalist/persona.toml
personas/cast/journalist/prompt.md
personas/cast/little-ripper/persona.toml
personas/cast/little-ripper/prompt.md
personas/cast/popeye/persona.toml
personas/cast/popeye/prompt.md
personas/cast/quiet-kid/persona.toml
personas/cast/quiet-kid/prompt.md
personas/cast/smartest-guy/persona.toml
personas/cast/smartest-guy/system.md
personas/docs/output_examples.md
personas/src/__init__.py
personas/src/continue_utils.py
personas/src/kilocode_utils.py
personas/src/persona_utils.py
personas/src/personas.py
personas/src/system.md
pb_dolphin-0.1.13.data/data/kb/config_template.toml
pb_dolphin-0.1.13.dist-info/METADATA
pb_dolphin-0.1.13.dist-info/WHEEL
pb_dolphin-0.1.13.dist-info/entry_points.txt
pb_dolphin-0.1.13.dist-info/licenses/LICENSE.md
pb_dolphin-0.1.13.dist-info/RECORD
