Metadata-Version: 2.4
Name: pb-dolphin
Version: 0.1.13
Summary: Full-stack AI enablement platform
Project-URL: Homepage, https://plasticbeach.llc/
Project-URL: Documentation, https://github.com/plasticbeachllc/dolphin
Project-URL: Repository, https://github.com/plasticbeachllc/dolphin
Project-URL: Issues, https://github.com/plasticbeachllc/dolphin/issues
Project-URL: Changelog, https://github.com/plasticbeachllc/dolphin/blob/main/CHANGELOG.md
Author-email: "Plastic Beach, LLC" <info@plasticbeach.email>, tdc93 <taylor@plasticbeach.email>
Maintainer-email: "Plastic Beach, LLC" <info@plasticbeach.email>, tdc93 <taylor@plasticbeach.email>
License: MIT
License-File: LICENSE.md
Keywords: ai,knowledge-base,llm,mcp,search
Classifier: Development Status :: 4 - Beta
Classifier: Intended Audience :: Developers
Classifier: License :: OSI Approved :: MIT License
Classifier: Programming Language :: Python :: 3
Classifier: Programming Language :: Python :: 3.12
Classifier: Programming Language :: Python :: 3.13
Requires-Python: >=3.12
Requires-Dist: fastapi
Requires-Dist: lancedb
Requires-Dist: markdown-it-py
Requires-Dist: openai
Requires-Dist: pathspec
Requires-Dist: pydantic
Requires-Dist: python-dotenv
Requires-Dist: pyyaml
Requires-Dist: sqlite-utils
Requires-Dist: sqlmodel
Requires-Dist: tiktoken
Requires-Dist: tomli; python_full_version < '3.11'
Requires-Dist: tree-sitter-javascript>=0.25.0
Requires-Dist: tree-sitter-python>=0.25.0
Requires-Dist: tree-sitter>=0.25.0
Requires-Dist: typer
Requires-Dist: uvicorn
Provides-Extra: dev
Requires-Dist: black>=23.0.0; extra == 'dev'
Requires-Dist: isort>=5.12.0; extra == 'dev'
Requires-Dist: mypy>=1.5.0; extra == 'dev'
Requires-Dist: pre-commit>=3.4.0; extra == 'dev'
Requires-Dist: ruff>=0.1.0; extra == 'dev'
Provides-Extra: reranking
Requires-Dist: sentence-transformers>=2.3.0; extra == 'reranking'
Requires-Dist: torch>=2.2.0; extra == 'reranking'
Provides-Extra: test
Requires-Dist: fakeredis>=2.18.0; extra == 'test'
Requires-Dist: freezegun>=1.2.0; extra == 'test'
Requires-Dist: httpx>=0.25.0; extra == 'test'
Requires-Dist: pytest-asyncio>=0.21.0; extra == 'test'
Requires-Dist: pytest-cov>=4.1.0; extra == 'test'
Requires-Dist: pytest-mock>=3.11.0; extra == 'test'
Requires-Dist: pytest-xdist>=3.3.0; extra == 'test'
Requires-Dist: pytest>=7.4.0; extra == 'test'
Requires-Dist: responses>=0.24.0; extra == 'test'
